ovcontrolnet_tools/__init__.py
ovcontrolnet_tools/conversion.py
ovcontrolnet_tools/main.py
ovcontrolnet_tools/models.py
ovcontrolnet_tools/options.py
ovcontrolnet_tools/pipe.py
ovcontrolnet_tools/utils.py
ovcontrolnet_tools-1.0.2.dist-info/METADATA
ovcontrolnet_tools-1.0.2.dist-info/WHEEL
ovcontrolnet_tools-1.0.2.dist-info/top_level.txt
ovcontrolnet_tools-1.0.2.dist-info/RECORD
