Metadata-Version: 2.1
Name: ovcontrolnet-tools
Version: 1.0.2
Summary: Packages for simple implementations of OVControlNet
Home-page: https://github.com/suk-6/ovcontrolnet-tools
Author: suk-6
Author-email: me@suk.kr
License: MIT
Requires-Python: >=3.6
Requires-Dist: torch
Requires-Dist: openvino
Requires-Dist: controlnet-aux
Requires-Dist: diffusers
Requires-Dist: transformers
Requires-Dist: matplotlib
Requires-Dist: accelerate
Requires-Dist: mediapipe
